{"authority_admin-page.md":"C3VqP7UY","authority_index.md":"BOVR99wJ","authority_manage.md":"B2tipYIL","contract_details.md":"e74qI8S4","contract_index.md":"CTYfvW9s","contract_release.md":"CzOggLFp","contract_status.md":"CHOxf-wg","contract_succession.md":"DZdSw4qK","document_index.md":"B3cjCUj_","document_legal-case.md":"aV_1kno1","document_legal-docs.md":"D-1V-HwN","index.md":"CaRyCi91","intro_getting-started.md":"Covaxz0o","ledger_imprest.md":"fWAMjlnh","ledger_manage.md":"Bh-80xlP","ledger_status.md":"75q42NaR","notice_bill.md":"BggslH_2","notice_sms.md":"DnOU4B40","payment_index.md":"D5JAgb_p","payment_manage.md":"ib_ch5q4","payment_status.md":"CF6Y6KNA","project_budgets.md":"UtuX3r19","project_index.md":"CV9v-IWJ","project_settings.md":"XuCV9532","project_site-manage.md":"DUOjjKk4","project_types.md":"Di88hU9m","project_units.md":"DTk0qPLl","work-manage_activity.md":"jXOEzX9T","work-manage_calendar.md":"COmzrN7D","work-manage_docs.md":"Dvk6pG4S","work-manage_forum.md":"BGSSMTrQ","work-manage_issue.md":"BUfywq4m","work-manage_meeting.md":"BC4FhR-i","work-manage_news.md":"9kOM5ry0","work-manage_project.md":"NFrZKjHs","work-manage_roadmap.md":"2ufC1WDT","work-manage_settings.md":"NJkBH1eg","work-setting_roll-perm.md":"flwng6gn","work-setting_user.md":"BGEDns45"}
