{"authority_admin-page.md":"B_x19dr_","authority_index.md":"CdEYSKqY","authority_manage.md":"DAFkFi4i","contract_details.md":"DP5a5qkZ","contract_index.md":"D_6kbDZF","contract_release.md":"CoY0vGeQ","contract_status.md":"CX9YOr5D","contract_succession.md":"CszqUknM","document_index.md":"C00pjfre","document_legal-case.md":"D2tJ90yw","document_legal-docs.md":"Co3S_p9L","index.md":"oZMHdY0m","intro_getting-started.md":"C88sE7gu","ledger_imprest.md":"DP2lm25Y","ledger_manage.md":"CwcBAuKl","ledger_status.md":"B_tUZGhF","notice_bill.md":"BIb7LtbT","notice_sms.md":"FWUYoa_7","payment_index.md":"DYHa74Y2","payment_manage.md":"DRsGi0ju","payment_status.md":"C3ZEcYP1","project_budgets.md":"BNMa3oTF","project_index.md":"AJRNsN3h","project_settings.md":"BVo0ERh4","project_site-manage.md":"CO9O9kfA","project_types.md":"D821f-WR","project_units.md":"DrLkd9Gv","work-manage_activity.md":"DVC_r-L_","work-manage_calendar.md":"XP1uV1F3","work-manage_docs.md":"CCZz6Way","work-manage_forum.md":"b-4RR9mV","work-manage_issue.md":"BE30LSUs","work-manage_meeting.md":"CY3xv_Qr","work-manage_news.md":"BJp5rzJW","work-manage_project.md":"B2j0KMYc","work-manage_roadmap.md":"D7L4urjq","work-manage_settings.md":"CbseQCdV","work-setting_roll-perm.md":"0hWsM1gG","work-setting_user.md":"C4tYL8sZ"}
