{"authority_admin-page.md":"BNUddfzU","authority_index.md":"C6aBtTCv","cashes_manage.md":"DFu6uA2V","cashes_settings.md":"g8PdaGjC","contract_bill-notice.md":"Y40sdAVZ","contract_index.md":"Biwv7m4Q","contract_payment.md":"NO0fi5rB","contract_release.md":"D1UQco9w","document_index.md":"Cb5DN2Sx","document_legal-case.md":"KmoJArjW","index.md":"jjajwMIP","intro_getting-started.md":"m2x4wAq3","settings_company.md":"Bfgtv3Zl","settings_details.md":"BIrpJHFA","settings_project.md":"CUdIhAt3","settings_site-manage.md":"Dw3YfDJ2"}
