{"authority_admin-page.md":"D4AxL3Sg","authority_index.md":"BvwoXLD3","cashes_manage.md":"DAEST6IL","cashes_settings.md":"PRlVPB9v","contract_bill-notice.md":"DduUMIi7","contract_index.md":"DP01xu3L","contract_payment.md":"CQWj0vaL","contract_release.md":"8OOxH5my","document_index.md":"BvvQHZxu","document_legal-case.md":"B6eqpVDf","index.md":"xixN7kYi","intro_getting-started.md":"DYfbFJTz","settings_company.md":"B45FjBWK","settings_details.md":"BNUX4qNt","settings_project.md":"BwcpG1in","settings_site-manage.md":"BtN7mify"}
