{"authority_admin-page.md":"DTHfFI3M","authority_index.md":"BqbfLXyd","cashes_manage.md":"BhSXFxvw","cashes_settings.md":"QPM8kJSG","contract_bill-notice.md":"hFkHAZA6","contract_index.md":"COJ-BhNu","contract_payment.md":"B0m1PEU6","contract_release.md":"ClEsTIxt","document_index.md":"BxxzAklk","document_legal-case.md":"BEZ-_BxM","index.md":"DMmdVaww","intro_getting-started.md":"D4ZOBWq5","settings_company.md":"Dl-zpFel","settings_details.md":"B_FBRnzV","settings_project.md":"MCZ2uTZY","settings_site-manage.md":"BXEMu7Fe"}
