{"authority_admin-page.md":"BxFhG81C","authority_index.md":"BEdTLql3","cashes_manage.md":"CKjnJA_y","cashes_settings.md":"CPeHOnpd","contract_bill-notice.md":"Dl0JQDp8","contract_index.md":"mh0HAE_I","contract_payment.md":"e6PFUV7N","contract_release.md":"BeR1iPrZ","document_index.md":"dZ6XKSbw","document_legal-case.md":"B4ssUXoe","index.md":"eJNKYnnS","intro_getting-started.md":"CIi54PjH","settings_company.md":"Bo1mlX8O","settings_details.md":"DSbeem0V","settings_project.md":"CwfNkPMp","settings_site-manage.md":"CSit-i38"}
