{"authority_admin-page.md":"DPK5UIiJ","authority_index.md":"Dza3U4pu","authority_manage.md":"Bp7h7czL","contract_details.md":"Eg4XbiYQ","contract_index.md":"BVlfQr0D","contract_release.md":"CpgAoB-l","contract_status.md":"CAcK8Aq5","contract_succession.md":"CDB3bLUo","document_index.md":"ClhHy4AQ","document_legal-case.md":"D7NlQ1AJ","document_legal-docs.md":"BU8VJadc","index.md":"X8Cx4Si0","intro_getting-started.md":"vaSjY6ti","ledger_imprest.md":"EY0WGkYm","ledger_manage.md":"CSv8pL6Y","ledger_status.md":"CejG2ZvB","notice_bill.md":"FjKXoMtA","notice_sms.md":"BPtg_BfH","payment_index.md":"DFBiCspD","payment_manage.md":"CFbXLyKA","payment_status.md":"BuEMcXHR","project_budgets.md":"DosWjoxh","project_index.md":"BpW78y-U","project_settings.md":"CN0CnMEe","project_site-manage.md":"saH9IlQ0","project_types.md":"DAPEC6NU","project_units.md":"C2oBa_op","work-manage_activity.md":"BU1_twRR","work-manage_calendar.md":"DM0AH6dW","work-manage_docs.md":"Dm8Fjn1I","work-manage_forum.md":"cuxS91AE","work-manage_issue.md":"BPHfSQQG","work-manage_meeting.md":"Dcb0f0Hd","work-manage_news.md":"IEc0umpp","work-manage_project.md":"BEjiUUL8","work-manage_roadmap.md":"DM6cUF8X","work-manage_settings.md":"BNdF1yed","work-setting_roll-perm.md":"BJ5F3kla","work-setting_user.md":"DvoGdt-d"}
