{"authority_admin-page.md":"y82F2uE4","authority_index.md":"BteqX3Ay","authority_manage.md":"DT7SgKFU","contract_details.md":"DFhTcc4R","contract_index.md":"BZPZos94","contract_release.md":"fiv6TdSE","contract_status.md":"DE00-1e7","contract_succession.md":"TGiRSG7d","document_index.md":"BhkmpgwD","document_legal-case.md":"Ct07gjb-","document_legal-docs.md":"DtOnQi5D","index.md":"DmmyQ2iE","intro_getting-started.md":"Bi7dn3LO","ledger_imprest.md":"Dhp9z-h2","ledger_manage.md":"D2hhyjNh","ledger_status.md":"bAeM2MI3","notice_bill.md":"CQuxNQUz","notice_sms.md":"DW53TdIA","payment_index.md":"DxxfBvPO","payment_manage.md":"BUBSOMqg","payment_status.md":"BN1aFrKr","project_budgets.md":"b7_VZQoG","project_index.md":"DtpySnrk","project_settings.md":"BdMQrVAz","project_site-manage.md":"CCrSecPo","project_types.md":"DI4FJ0Uc","project_units.md":"BybWC_g_","work-manage_activity.md":"DR55od2m","work-manage_calendar.md":"akxXzRrj","work-manage_docs.md":"BUCzr0sr","work-manage_forum.md":"Dm35gk4g","work-manage_issue.md":"BoTuf7tE","work-manage_meeting.md":"CaX9jQJv","work-manage_news.md":"CCRrXBG4","work-manage_project.md":"CYbB4UvM","work-manage_roadmap.md":"B0OxQafz","work-manage_settings.md":"C8IYS6AQ","work-setting_roll-perm.md":"DzGZTABw","work-setting_user.md":"DeXUYIL2"}
