{"authority_admin-page.md":"txrA-n-P","authority_index.md":"MhwluCVd","contract_details.md":"CD1vJ116","contract_index.md":"Dxxa2i7P","contract_release.md":"D2398dxP","contract_status.md":"BXG6K7Fw","contract_succession.md":"Cp6nGUqJ","document_index.md":"C11UlPMt","document_legal-case.md":"DQROfWF5","document_legal-docs.md":"71DA3rEq","index.md":"BaH6pPoG","intro_getting-started.md":"7ieA6S-U","ledger_imprest.md":"D-wZNSmT","ledger_manage.md":"BTr2JrR-","ledger_status.md":"Ba35vwuV","notice_bill.md":"CZNXaRs1","notice_sms.md":"B9WMOPnz","payment_index.md":"YAk1IVkZ","payment_manage.md":"BOYoasxH","payment_status.md":"CTcyLcj9","project_budgets.md":"CWbna0vA","project_index.md":"DdrIilEC","project_settings.md":"CJWd3hKR","project_site-manage.md":"Ck7rPVdV","project_types.md":"CqZGm1dy","project_units.md":"D7I0kyQt"}
