{"authority_admin-page.md":"D5gKC0Mt","authority_index.md":"Bh_jTcs8","cashes_manage.md":"B3CLEOzu","cashes_settings.md":"CnU5VOSs","contract_bill-notice.md":"vnz7ZaKx","contract_index.md":"CwSNygP9","contract_payment.md":"DTuepB8s","contract_release.md":"FMyY6ZAB","document_index.md":"ou50GQ5a","document_legal-case.md":"DRMIlybL","index.md":"33nGU0LV","intro_getting-started.md":"CVErwNkx","settings_company.md":"Cx8dRiga","settings_details.md":"DjKba8bs","settings_project.md":"CZ9csCQE","settings_site-manage.md":"sYfzoEzf"}
