{"authority_admin-page.md":"DROZfADI","authority_index.md":"BHMQFHRw","cashes_manage.md":"obTcTcDI","cashes_settings.md":"Bo5Xz-HY","contract_bill-notice.md":"AkLjGPGF","contract_index.md":"CY8T8MJD","contract_payment.md":"Cw4NBxzb","contract_release.md":"C2DxQPzw","document_index.md":"BFBO0-uw","document_legal-case.md":"zk9BzCaO","index.md":"Du0WnCvd","intro_getting-started.md":"XYyPJRae","settings_company.md":"CAE8fdvi","settings_details.md":"DAsBnk7m","settings_project.md":"DZjsxMJD","settings_site-manage.md":"TH1ELRfL"}
