{"authority_admin-page.md":"9o1Uzy_1","authority_index.md":"De4PSpok","authority_manage.md":"C3u6afmd","contract_details.md":"y6Y0zFnC","contract_index.md":"yETviijr","contract_release.md":"Ce1NBPP7","contract_status.md":"B_70SFhF","contract_succession.md":"BVMsruDv","document_index.md":"DYvNWkXT","document_legal-case.md":"DCgL4T5S","document_legal-docs.md":"BY7SpLjR","index.md":"BlDcS-Qi","intro_getting-started.md":"OIf3tGpN","ledger_imprest.md":"tTIRNcog","ledger_manage.md":"D94R_0VK","ledger_status.md":"BAg30GEd","notice_bill.md":"D9PlsIdf","notice_sms.md":"hys2HeEG","payment_index.md":"DKZooYf8","payment_manage.md":"B94dL_Jb","payment_status.md":"g-sYe_qY","project_budgets.md":"BddmYkuo","project_index.md":"ouOjnwtj","project_settings.md":"CS1tvB2L","project_site-manage.md":"BKgzot4k","project_types.md":"CLk02_4C","project_units.md":"B4GV-mIU","work-manage_activity.md":"DB57rFsG","work-manage_calendar.md":"4NbBMbVk","work-manage_docs.md":"D8qpKorE","work-manage_forum.md":"to3rLidI","work-manage_issue.md":"BIBZYfB6","work-manage_meeting.md":"D1oRlvep","work-manage_news.md":"VFzqUNZi","work-manage_project.md":"IW75s3ey","work-manage_roadmap.md":"BXGgdhPB","work-manage_settings.md":"CqX_J53M","work-setting_roll-perm.md":"BmzzqxTY","work-setting_user.md":"9op9tkp6"}
