{"authority_admin-page.md":"ChXysVWl","authority_index.md":"ikVgwrbW","cashes_manage.md":"CYlKqA71","cashes_settings.md":"DCykRYWK","contract_bill-notice.md":"C6BypY8B","contract_index.md":"zez11B2-","contract_payment.md":"C8A0PsC5","contract_release.md":"f1NY1iOh","document_index.md":"BgcRV7ll","document_legal-case.md":"CsJaoWsM","index.md":"CbzmsaYj","intro_getting-started.md":"BznREDhJ","settings_company.md":"CPgMDKaf","settings_details.md":"CsdEiYtu","settings_project.md":"DO0wxYhP","settings_site-manage.md":"CF1_orZk"}
