{"cashes_manage.md":"38d5e288","contract_index.md":"23224483","document_legal-case.md":"f213a5b6","cashes_settings.md":"d8e165d1","contract_payment.md":"009afe7b","contract_bill-notice.md":"27a1c5a9","settings_details.md":"d8bf8e15","settings_company.md":"e5f1c159","intro_getting-started.md":"791b302b","settings_site-manage.md":"bee08194","authority_admin-page.md":"c5960579","settings_project.md":"778a6fea","contract_release.md":"b10d7eb6","document_index.md":"6b517c35","authority_index.md":"63e353b9","index.md":"4546f00e"}
