{"authority_admin-page.md":"ByEYYZmx","authority_index.md":"BCd0Shi-","cashes_manage.md":"CvUC0n1Z","cashes_settings.md":"D4Azxc_M","contract_bill-notice.md":"sMcpmZZH","contract_index.md":"DvsdLLjB","contract_payment.md":"Fe9JLbzE","contract_release.md":"DSG1nEW9","document_index.md":"p4Pl159J","document_legal-case.md":"DwDHBC69","index.md":"BA7VMJDw","intro_getting-started.md":"D-NTkcHn","settings_company.md":"BmTa_y34","settings_details.md":"DzCQyQCG","settings_project.md":"Bk35Az2i","settings_site-manage.md":"DdX6fzBj"}
