{"authority_admin-page.md":"D4GyosyB","authority_index.md":"C8Nhn6CG","cashes_manage.md":"CoZ3jx3l","cashes_settings.md":"BricegG-","contract_bill-notice.md":"BXS7HuBF","contract_index.md":"BB0yZyCu","contract_payment.md":"BywwBIkP","contract_release.md":"Bml9oHnO","document_index.md":"DV5V2v8n","document_legal-case.md":"ByigrYxk","index.md":"BXWqp88e","intro_getting-started.md":"B_Vzld6y","settings_company.md":"BTTK8HOU","settings_details.md":"B8ldfmpN","settings_project.md":"B8Srw1DU","settings_site-manage.md":"CrptBZKG"}
