{"authority_admin-page.md":"FiC8uxKx","authority_index.md":"BVXUhRFi","cashes_manage.md":"DtcLZQ_j","cashes_settings.md":"BUz45_hM","contract_bill-notice.md":"Dnjv6WVB","contract_index.md":"3SufYI4z","contract_payment.md":"BOvRBOhz","contract_release.md":"Bk6pQJAl","document_index.md":"tk17g9aI","document_legal-case.md":"C9zp1lOo","index.md":"DxVC3W01","intro_getting-started.md":"D8Yh_B7r","settings_company.md":"BUnJCOPx","settings_details.md":"B2Go11_y","settings_project.md":"CgOq5AYk","settings_site-manage.md":"g1upRq_3"}
