{"authority_admin-page.md":"CYW1rgYj","authority_index.md":"C_LxKwY7","cashes_manage.md":"Dqb0THJX","cashes_settings.md":"jS9RqZbV","contract_bill-notice.md":"Dj0KkBtu","contract_index.md":"g5eb40JN","contract_payment.md":"Dkty8iw8","contract_release.md":"CT1mQlWo","document_index.md":"DuGmvxyf","document_legal-case.md":"CiZ5Sgap","index.md":"DG45Zx3S","intro_getting-started.md":"D9EccrfU","settings_company.md":"BBMpnmB1","settings_details.md":"DwsbUhht","settings_project.md":"DvvsU8U3","settings_site-manage.md":"CaKZVVOo"}
