{"authority_admin-page.md":"B-OZapb-","authority_index.md":"BDHz5k6y","cashes_manage.md":"BBVxHzh4","cashes_settings.md":"CGcdkjJ6","contract_bill-notice.md":"CpqG6ln2","contract_index.md":"s8sEPjJK","contract_payment.md":"Cbu6U6WD","contract_release.md":"CWZ9b2GU","document_index.md":"D5BmVL3F","document_legal-case.md":"ms5yQBfj","index.md":"D1ft5CNi","intro_getting-started.md":"B-DfHiP2","settings_company.md":"DIDjJuy0","settings_details.md":"D78vsYh4","settings_project.md":"D-fEcmGD","settings_site-manage.md":"D8Bw8BAN"}
