{"authority_admin-page.md":"CG2rYexf","authority_index.md":"Bl0wp406","cashes_manage.md":"iWWUv31o","cashes_settings.md":"Budzkfx_","contract_bill-notice.md":"BVsz4CWr","contract_index.md":"CpmipclF","contract_payment.md":"D14CMXhU","contract_release.md":"Cv2db41i","document_index.md":"BmdWuSdy","document_legal-case.md":"B-4mHRwm","index.md":"DGcSOPML","intro_getting-started.md":"DtXSwBAA","settings_company.md":"DN5U35pD","settings_details.md":"qGDKE3W-","settings_project.md":"BhMkTFZq","settings_site-manage.md":"B8AvcgbE"}
