{"index.md":"7d31df14","authority_admin-page.md":"cded412f","settings_details.md":"e860b41d","intro_getting-started.md":"aeea8d23","settings_company.md":"efc32657","contract_bill-notice.md":"d5ddf0f4","settings_site-manage.md":"a57c6d69","settings_project.md":"4ace59ba","authority_index.md":"3c7e843a","contract_payment.md":"e010319f","cashes_settings.md":"2115b6ac","document_index.md":"796ef084","document_legal-case.md":"4b816b86","contract_release.md":"f617e501","contract_index.md":"370a03c1","cashes_manage.md":"602305a8"}
