{"authority_admin-page.md":"sX-J7HIs","authority_index.md":"B6mu-jKS","cashes_manage.md":"z71WbSP4","cashes_settings.md":"Ct1m81Wy","contract_bill-notice.md":"DIzoF67R","contract_index.md":"DDMkSgl6","contract_payment.md":"CfMLZ51S","contract_release.md":"CUIM0nji","document_index.md":"BHYTWFOI","document_legal-case.md":"BQemVsLg","index.md":"PkY5w6st","intro_getting-started.md":"BT0FtSoJ","settings_company.md":"Bn-f5Glr","settings_details.md":"r2and1eE","settings_project.md":"Do__FZEm","settings_site-manage.md":"ByabUcBg"}
