{"authority_admin-page.md":"ByZdiiFz","authority_index.md":"BQ6x_TQ9","cashes_manage.md":"DjhnPx4i","cashes_settings.md":"BvZJ7lHp","contract_bill-notice.md":"DehKVGfU","contract_index.md":"CQwR7vJk","contract_payment.md":"Dbced-nE","contract_release.md":"7cVLGkD8","document_index.md":"ON-TNZfp","document_legal-case.md":"CFtFv28N","index.md":"DZw1jxob","intro_getting-started.md":"DPcrCPXX","settings_company.md":"DOXo1W2V","settings_details.md":"BHOATFRl","settings_project.md":"OP5Um1PK","settings_site-manage.md":"h_gXcdjB"}
