{"authority_admin-page.md":"BVr64xtF","authority_index.md":"Dfsq1_9x","cashes_manage.md":"R40S_4e2","cashes_settings.md":"DA7zBhub","contract_bill-notice.md":"BGS0Cstw","contract_index.md":"D_M9Znua","contract_payment.md":"CjjLDGWj","contract_release.md":"nTlUzMV7","document_index.md":"CC3k14xd","document_legal-case.md":"RDUsxJmi","index.md":"Dq7oroN6","intro_getting-started.md":"By0lZfaP","settings_company.md":"BeR15M0z","settings_details.md":"BDmmCVQs","settings_project.md":"D73IEoB7","settings_site-manage.md":"DXYnUUpt"}
