{"authority_admin-page.md":"Dyk8W0Xi","authority_index.md":"BR1vBWkT","authority_manage.md":"DPC04Ech","contract_details.md":"CXfijHgu","contract_index.md":"BXQAxUwN","contract_release.md":"BdkgtWye","contract_status.md":"CEEmDep6","contract_succession.md":"Dp_keFFt","document_index.md":"qrtLcirc","document_legal-case.md":"Af1mV7d7","document_legal-docs.md":"Bv5KC5Ye","index.md":"9S9AQJBE","intro_getting-started.md":"5TErneAg","ledger_imprest.md":"F72aSyTe","ledger_manage.md":"DpUIeFHT","ledger_status.md":"Dx9PUW17","notice_bill.md":"BeQ695ti","notice_sms.md":"vUHMzK6r","payment_index.md":"D0xL-g5i","payment_manage.md":"D_OYX5A9","payment_status.md":"BZ--L-MZ","project_budgets.md":"BMHT_8tQ","project_index.md":"CiHN3H7w","project_settings.md":"BPhM5lq8","project_site-manage.md":"CVZz4XOE","project_types.md":"BipUN-x6","project_units.md":"Cqj9t6N6","work-manage_activity.md":"BkwBQfIp","work-manage_calendar.md":"B3Lttz_X","work-manage_docs.md":"_7eXul2V","work-manage_forum.md":"DRMs4cRK","work-manage_issue.md":"BMkYW8ix","work-manage_meeting.md":"DgV0l35K","work-manage_notice.md":"BaxXIzjd","work-manage_project.md":"-nHmScOd","work-manage_roadmap.md":"B6KKbEQ3","work-manage_settings.md":"CnZiKg7F","work-setting_roll.md":"BWdVkiZR","work-setting_user.md":"C4Hhuiux"}
