{"authority_admin-page.md":"CLOhzYRK","authority_index.md":"DF9nh25Q","cashes_manage.md":"B0vzMOzm","cashes_settings.md":"Pr1fYbZQ","contract_bill-notice.md":"xD1rxdYc","contract_index.md":"xdaVuZJ9","contract_payment.md":"BKHJ_bIs","contract_release.md":"B_zkzCu1","document_index.md":"B69XHPM2","document_legal-case.md":"CpJNWDXV","index.md":"wnp968HC","intro_getting-started.md":"DoCzi09l","settings_company.md":"C6nS7Ryv","settings_details.md":"DprDYy7w","settings_project.md":"0NaHf5Gs","settings_site-manage.md":"Rf3nE4bq"}
