{"authority_admin-page.md":"BeUXKPNr","authority_index.md":"DCzxx47f","authority_manage.md":"DElJprUO","contract_details.md":"ZZ0fxuY2","contract_index.md":"CHvI-KfC","contract_release.md":"D9Ey4bY_","contract_status.md":"DVRrcyMR","contract_succession.md":"BiSRArwv","document_index.md":"B9LeLYWa","document_legal-case.md":"CqAHOJHV","document_legal-docs.md":"DvnQdR8z","index.md":"tIsT6Grn","intro_dashboard.md":"Cyn81s8_","intro_getting-started.md":"DDL9ZHsH","ledger_imprest.md":"Bxp4jYag","ledger_manage.md":"D9hIHEBp","ledger_status.md":"BqaCCLqo","notice_bill.md":"AaFUCkuM","notice_sms.md":"Dzo0EpXo","payment_index.md":"-zhvvBaf","payment_manage.md":"CqRKXQsT","payment_status.md":"Cpnt_oTs","project_budgets.md":"CqdWFZt7","project_index.md":"DXCsppYT","project_settings.md":"DLo9vQqO","project_site-manage.md":"m-4H-vRs","project_types.md":"CxONEL-R","project_units.md":"CYlmNbbL","work-manage_activity.md":"CSnJXnrq","work-manage_calendar.md":"DHQmPvOD","work-manage_docs.md":"Davheik9","work-manage_forum.md":"eDOPXH9Y","work-manage_issue.md":"_P-mHGYf","work-manage_meeting.md":"B1T3MMUj","work-manage_news.md":"DGheAdc6","work-manage_project.md":"CYG4ZE2h","work-manage_roadmap.md":"C73h_fS_","work-manage_settings.md":"n97iZYmA","work-setting_roll-perm.md":"CJT_fz_U","work-setting_user.md":"CbB163bo"}
