{"authority_admin-page.md":"ea2fbbc2","settings_details.md":"beffcdf4","contract_payment.md":"ca2ed5e3","intro_getting-started.md":"9f12cc36","contract_index.md":"5bc5d91a","cashes_settings.md":"0b62156f","index.md":"cac94bd6","document_legal-case.md":"5b075a06","document_index.md":"8892bd55","contract_bill-notice.md":"a92a636c","authority_index.md":"52268951","settings_company.md":"410c7010","contract_release.md":"80d0a963","cashes_manage.md":"6af610f6","settings_project.md":"cb94ef1d","settings_site-manage.md":"18666977"}
