{"authority_admin-page.md":"_3o5FMNT","authority_index.md":"CjhgBUyE","cashes_manage.md":"B54S2v9F","cashes_settings.md":"c5HzGDzS","contract_bill-notice.md":"DOR-7_-Q","contract_index.md":"BNqsSHn6","contract_payment.md":"Bm2hn2OG","contract_release.md":"BtfdZvb_","document_index.md":"BL0dCm4x","document_legal-case.md":"D4asEpln","index.md":"BzXqymd-","intro_getting-started.md":"C_D7hR8X","settings_company.md":"_kXzXeyi","settings_details.md":"BLbcebcw","settings_project.md":"o2ju4333","settings_site-manage.md":"DP8rfUJ8"}
