{"authority_admin-page.md":"CcBfnoXo","authority_index.md":"BtOwofZb","cashes_manage.md":"rZw1d-2w","cashes_settings.md":"CW_63EAC","contract_bill-notice.md":"BWrLXD56","contract_index.md":"D_nfH6BF","contract_payment.md":"C4gp979l","contract_release.md":"DE68z4sh","document_index.md":"D1wRm2BL","document_legal-case.md":"DQEopwcO","index.md":"SW77afZr","intro_getting-started.md":"CzastCcl","settings_company.md":"DeY27rg3","settings_details.md":"DJIuL0wi","settings_project.md":"GlJ4EGeo","settings_site-manage.md":"BeDbZipi"}
